{"error": null, "response": {"classes": [], "funcs": [{"docstring": {"func": "Main executable function.", "long_descr": null, "ret": null}, "fn_lc": [[39, 0], [48, 19]], "fn_var_ln": {"args": [[47, 4], [47, 8]], "conf": [[41, 4], [41, 8]], "parser": [[45, 4], [45, 10]]}, "fn_var_occur": {"args": [["args", "parser", "parse_args"], ["args", "func", "args"]], "conf": [["conf", "configuration", "conf"], ["conf", "get"], ["os", "environ", "conf", "get"], ["os", "environ", "conf", "get"]], "parser": [["parser", "cli_parser", "get_parser"], ["argcomplete", "autocomplete", "parser"], ["args", "parser", "parse_args"]]}, "name": "main", "params": {}, "params_descr": {}, "params_occur": {}, "params_p": {"args": [], "kwargs": []}, "q_name": "main", "ret_exprs": [], "ret_type": "", "variables": {"args": "", "conf": "", "parser": ""}, "variables_p": {"args": [["List[Union[int, str]]", 0.09704718030962724], ["list", 0.09704718030962724], ["tuple", 0.07948144734520601], ["List[str]", 0.06987817095694143]], "conf": [], "parser": []}}], "imports": ["__future__", "annotations", "os", "argcomplete", "airflow", "configuration", "airflow", "cli", "cli_parser"], "mod_var_ln": {}, "mod_var_occur": {}, "no_types_annot": {"D": 0, "I": 0, "U": 4}, "session_id": "UiHAeAFE7VETdEYS-zHEpZzvnHXCogVOQLeD-w5_Uic", "set": null, "tc": [false, null], "type_annot_cove": 0.0, "typed_seq": "", "untyped_seq": "", "variables": {}, "variables_p": {}}}