{"error": null, "response": {"classes": [{"cls_lc": [[25, 0], [70, 49]], "cls_var_ln": {}, "cls_var_occur": {}, "funcs": [{"docstring": {"func": null, "long_descr": null, "ret": null}, "fn_lc": [[27, 4], [36, 19]], "fn_var_ln": {"term": [[34, 16], [34, 20]]}, "fn_var_occur": {"term": [["isinstance", "term", "list", "len", "term"], ["term", "term"], ["isinstance", "term", "list"], ["term", "self", "_check_list_of_one_list", "term"]]}, "name": "_check_list_of_one_list", "params": {"self": "", "term": ""}, "params_descr": {"self": "", "term": ""}, "params_occur": {"self": [["term", "self", "_check_list_of_one_list", "term"]], "term": [["isinstance", "term", "list", "len", "term"], ["term", "term"], ["isinstance", "term", "list"], ["term", "self", "_check_list_of_one_list", "term"]]}, "params_p": {"args": [], "kwargs": [], "self": [], "term": [["list", 0.23552842705588162], ["str", 0.10803375142175226], ["List[int]", 0.09963855593248074], ["List[str]", 0.08702808664570602], ["Set[cmk.utils.type_defs.HostName]", 0.07972494527470403]]}, "q_name": "LookupModule._check_list_of_one_list", "ret_exprs": ["return term"], "ret_type": "", "ret_type_p": [["int", 0.2123559509069396], ["Tuple[int]", 0.1108687261349697], ["Sequence[int]", 0.10530133250135812], ["Sequence", 0.08169857178488153], ["List[int]", 0.07882644729459513]], "variables": {"term": ""}, "variables_p": {"term": [["list", 0.7223494790114774], ["List[str]", 0.10313737647899597], ["List[Tuple[int, int, int]]", 0.08399195605233552]]}}, {"docstring": {"func": null, "long_descr": null, "ret": null}, "fn_lc": [[38, 4], [62, 18]], "fn_var_ln": {"ret": [[40, 8], [40, 11]], "term": [[57, 16], [57, 20]], "term2": [[50, 16], [50, 21]]}, "fn_var_occur": {"ret": [["ret", "extend", "term"], ["ret", "append", "term"]], "term": [["term", "self", "_check_list_of_one_list", "term"], ["term", "term"], ["isinstance", "term", "string_types"], ["term2", "listify_lookup_plugin_terms", "term", "templar", "self", "_templar", "loader", "self", "_loader"], ["term2", "term"], ["term", "term2"], ["isinstance", "term", "list"], ["term", "self", "_do_flatten", "term", "variables"], ["ret", "extend", "term"], ["ret", "append", "term"]], "term2": [["term2", "listify_lookup_plugin_terms", "term", "templar", "self", "_templar", "loader", "self", "_loader"], ["term2", "term"], ["term", "term2"]]}, "name": "_do_flatten", "params": {"self": "", "terms": "", "variables": ""}, "params_descr": {"self": "", "terms": "", "variables": ""}, "params_occur": {"self": [["term", "self", "_check_list_of_one_list", "term"], ["term2", "listify_lookup_plugin_terms", "term", "templar", "self", "_templar", "loader", "self", "_loader"], ["term", "self", "_do_flatten", "term", "variables"]], "terms": [], "variables": [["term", "self", "_do_flatten", "term", "variables"]]}, "params_p": {"args": [], "kwargs": [], "self": [], "terms": [["str", 0.29164924895256666], ["UnicodeError", 0.29164924895256666], ["Callable", 0.1780414706851032]], "variables": [["Callable", 0.09399945299617214], ["Callable[[str], bool]", 0.09088296909818232]]}, "q_name": "LookupModule._do_flatten", "ret_exprs": ["return ret"], "ret_type": "", "ret_type_p": [["bool", 0.23253629142177515], ["List[str]", 0.2071718111504107], ["Set[str]", 0.17166549090752697], ["str", 0.09476334042230948], ["Dict[str, Any]", 0.09142606555205939]], "variables": {"ret": "", "term": "", "term2": ""}, "variables_p": {"ret": [["dict", 0.31225093753449296], ["Tuple[int, int, int, int, int, int]", 0.14927844409505428], ["str", 0.10510876725793705], ["List[Dict[str, Any]]", 0.08363956071357542], ["Dict[str, Union[Any, Any]]", 0.08276791624245718], ["Dict[str, Any]", 0.08208006346573796], ["Dict[str, Union[dict, Any, Any, Any, Any, Any, Any]]", 0.08072511382170024]], "term": [["str", 1.0]], "term2": [["list", 0.14272532776937824]]}}, {"docstring": {"func": null, "long_descr": null, "ret": null}, "fn_lc": [[65, 4], [70, 49]], "fn_var_ln": {}, "fn_var_occur": {}, "name": "run", "params": {"kwargs": "", "self": "", "terms": "", "variables": ""}, "params_descr": {"kwargs": "", "self": "", "terms": "", "variables": ""}, "params_occur": {"kwargs": [], "self": [["self", "_do_flatten", "terms", "variables"]], "terms": [["isinstance", "terms", "list"], ["self", "_do_flatten", "terms", "variables"]], "variables": [["self", "_do_flatten", "terms", "variables"]]}, "params_p": {"args": [], "kwargs": [], "self": [], "terms": [["Iterable[str]", 0.13055007513092237], ["List[Type]", 0.10431005964692179], ["Tuple[int, str, List[str]]", 0.09436722688394711], ["int", 0.08747634045037657]], "variables": []}, "q_name": "LookupModule.run", "ret_exprs": ["return self._do_flatten(terms, variables)"], "ret_type": "", "ret_type_p": [["int", 0.309042708541626], ["float", 0.10039149959157474], ["tuple", 0.0915374707164492]], "variables": {}, "variables_p": {}}], "name": "LookupModule", "q_name": "LookupModule", "variables": {}, "variables_p": {}}], "funcs": [], "imports": ["__future__", "absolute_import", "division", "print_function", "ansible", "compat", "six", "string_types", "ansible", "errors", "AnsibleError", "ansible", "plugins", "lookup", "LookupBase", "ansible", "utils", "listify", "listify_lookup_plugin_terms"], "mod_var_ln": {"__metaclass__": [[18, 0], [18, 13]]}, "mod_var_occur": {"__metaclass__": []}, "no_types_annot": {"D": 0, "I": 0, "U": 13}, "session_id": "UzXROAicdvC60Du-OjU-1DtTDGX3cif-MuoM66l39gg", "set": null, "tc": [false, null], "type_annot_cove": 0.0, "typed_seq": "", "untyped_seq": "", "variables": {"__metaclass__": ""}, "variables_p": {"__metaclass__": [["str", 0.4], ["List[str]", 0.1], ["int", 0.1], ["raiden.utils.WithdrawAmount", 0.1], ["Dict[str, List[Any]]", 0.1], ["Tuple[str, str, str, str, str, str, str, str]", 0.1]]}}}