{"error": null, "response": {"classes": [{"cls_lc": [[34, 0], [141, 13]], "cls_var_ln": {"template_ext": [[65, 4], [65, 16]], "template_fields": [[64, 4], [64, 19]], "template_fields_renderers": [[66, 4], [66, 29]], "ui_color": [[67, 4], [67, 12]]}, "cls_var_occur": {"template_ext": [], "template_fields": [], "template_fields_renderers": [], "ui_color": []}, "funcs": [{"docstring": {"func": null, "long_descr": null, "ret": null}, "fn_lc": [[69, 4], [93, 34]], "fn_var_ln": {"create": [[87, 8], [87, 19]], "delimiter": [[89, 8], [89, 22]], "hive_auth": [[93, 8], [93, 22]], "hive_cli_conn_id": [[91, 8], [91, 29]], "hive_table": [[85, 8], [85, 23]], "partition": [[92, 8], [92, 22]], "recreate": [[88, 8], [88, 21]], "sql": [[84, 8], [84, 16]], "vertica_conn_id": [[90, 8], [90, 28]]}, "fn_var_occur": {"create": [["self", "create", "create"]], "delimiter": [["self", "delimiter", "str", "delimiter"]], "hive_auth": [["self", "hive_auth", "hive_auth"]], "hive_cli_conn_id": [["self", "hive_cli_conn_id", "hive_cli_conn_id"]], "hive_table": [["self", "hive_table", "hive_table"]], "partition": [["self", "partition", "partition"], ["self", "partition", "partition"]], "recreate": [["self", "recreate", "recreate"]], "sql": [["self", "sql", "sql"]], "vertica_conn_id": [["self", "vertica_conn_id", "vertica_conn_id"]]}, "name": "__init__", "params": {"create": "builtins.bool", "delimiter": "builtins.str", "hive_auth": "str | None", "hive_cli_conn_id": "builtins.str", "hive_table": "builtins.str", "kwargs": "typing.Any", "partition": "dict | None", "recreate": "builtins.bool", "self": "", "sql": "builtins.str", "vertica_conn_id": "builtins.str"}, "params_descr": {"create": "", "delimiter": "", "hive_auth": "", "hive_cli_conn_id": "", "hive_table": "", "kwargs": "", "partition": "", "recreate": "", "self": "", "sql": "", "vertica_conn_id": ""}, "params_occur": {"create": [["self", "create", "create"]], "delimiter": [["self", "delimiter", "str", "delimiter"]], "hive_auth": [["self", "hive_auth", "hive_auth"]], "hive_cli_conn_id": [["self", "hive_cli_conn_id", "hive_cli_conn_id"]], "hive_table": [["self", "hive_table", "hive_table"]], "kwargs": [["super", "__init__", "kwargs"]], "partition": [["self", "partition", "partition"], ["self", "partition", "partition"]], "recreate": [["self", "recreate", "recreate"]], "self": [["self", "sql", "sql"], ["self", "hive_table", "hive_table"], ["self", "partition", "partition"], ["self", "create", "create"], ["self", "recreate", "recreate"], ["self", "delimiter", "str", "delimiter"], ["self", "vertica_conn_id", "vertica_conn_id"], ["self", "hive_cli_conn_id", "hive_cli_conn_id"], ["self", "partition", "partition"], ["self", "hive_auth", "hive_auth"]], "sql": [["self", "sql", "sql"]], "vertica_conn_id": [["self", "vertica_conn_id", "vertica_conn_id"]]}, "params_p": {"args": [], "create": [["Optional[str]", 0.24446631980336814], ["contests.models.User", 0.2259452865149359], ["str", 0.16010085804215737], ["zerver.models.UserProfile", 0.12185510206574575], ["List[str]", 0.07085155545880269], ["bool", 0.07010341911110471]], "delimiter": [["str", 0.2092101387626418], ["int", 0.13227358401447795], ["Optional[int]", 0.1097122646244219]], "hive_auth": [["Optional[str]", 0.24446631980336814], ["contests.models.User", 0.2259452865149359], ["str", 0.16010085804215737], ["zerver.models.UserProfile", 0.12185510206574575], ["List[str]", 0.07085155545880269], ["bool", 0.07010341911110471]], "hive_cli_conn_id": [["Mapping[Any, str]", 0.10178039940532967], ["Dict[str, Dict[str, Any]]", 0.09711530822683567], ["int", 0.09711530822683567], ["List[str]", 0.09540686933294909], ["str", 0.09540686933294909]], "hive_table": [["str", 0.4879084090246642], ["Dict[Optional[str], str]", 0.11212215466569131], ["Optional[List[str]]", 0.11028343729267193], ["float", 0.10395080441470533], ["dict", 0.09534511445906285], ["Dict[str, str]", 0.09039008014320439]], "kwargs": [], "partition": [["Optional[str]", 0.24446631980336814], ["contests.models.User", 0.2259452865149359], ["str", 0.16010085804215737], ["zerver.models.UserProfile", 0.12185510206574575], ["List[str]", 0.07085155545880269], ["bool", 0.07010341911110471]], "recreate": [["Optional[str]", 0.24446631980336814], ["contests.models.User", 0.2259452865149359], ["str", 0.16010085804215737], ["zerver.models.UserProfile", 0.12185510206574575], ["List[str]", 0.07085155545880269], ["bool", 0.07010341911110471]], "self": [], "sql": [["Optional[str]", 0.24446631980336814], ["contests.models.User", 0.2259452865149359], ["str", 0.16010085804215737], ["zerver.models.UserProfile", 0.12185510206574575], ["List[str]", 0.07085155545880269], ["bool", 0.07010341911110471]], "vertica_conn_id": [["int", 0.3169163256647712], ["str", 0.28901308024221345], ["order.transfer.models.OrderNumberSequenceID", 0.10623536929348566], ["Optional[List[str]]", 0.10172066059447771], ["Dict[str, Dict[str, Any]]", 0.09645173402097756]]}, "q_name": "VerticaToHiveOperator.__init__", "ret_exprs": [], "ret_type": "None", "variables": {"create": "", "delimiter": "", "hive_auth": "", "hive_cli_conn_id": "", "hive_table": "", "partition": "", "recreate": "", "sql": "", "vertica_conn_id": ""}, "variables_p": {"create": [["str", 0.22162339950759935], ["float", 0.19246428563617257], ["bool", 0.11529802646449998], ["int", 0.08730758941570631]], "delimiter": [["int", 0.5320981647865644], ["str", 0.2752460699658259], ["Optional[int]", 0.08617918052850873]], "hive_auth": [["bool", 0.42613000262319056], ["int", 0.18984205252269754], ["str", 0.0990235562405609], ["Union[int, Tuple[int, int]]", 0.09478627033559957]], "hive_cli_conn_id": [["int", 0.7159134740564593], ["str", 0.19978316166978805], ["bool", 0.08430336427375282]], "hive_table": [["str", 0.48594683464344696], ["bool", 0.31071121451935096], ["csv.DictWriter", 0.09856001185339902]], "partition": [["int", 0.3], ["str", 0.19999999999999998], ["Tuple[int, int, int, int]", 0.09999999999999999], ["dict", 0.09999999999999999], ["List[str]", 0.09999999999999999], ["Tuple[Any, int]", 0.09999999999999999]], "recreate": [["str", 0.30000000000000004], ["Dict[str, Any]", 0.1], ["dict", 0.1], ["int", 0.1]], "sql": [["str", 0.30000000000000004], ["Dict[str, Any]", 0.1], ["dict", 0.1], ["int", 0.1]], "vertica_conn_id": [["int", 0.5314096773347922], ["str", 0.0976297101878023], ["transfer.models.ShopID", 0.0927401531193514], ["transfer.models.StorefronID", 0.0927401531193514], ["transfer.models.ArticleID", 0.0927401531193514]]}}, {"docstring": {"func": "Manually hack Vertica-Python type mapping.", "long_descr": "The stock datatype.py does not provide the full type mapping access.\n\nReference:\nhttps://github.com/uber/vertica-python/blob/master/vertica_python/vertica/column.py", "ret": null}, "fn_lc": [[96, 4], [112, 51]], "fn_var_ln": {"type_map": [[104, 8], [104, 16]]}, "fn_var_occur": {"type_map": [["type_map", "get", "vertica_type"]]}, "name": "type_map", "params": {"cls": "", "vertica_type": ""}, "params_descr": {"cls": "", "vertica_type": ""}, "params_occur": {"cls": [], "vertica_type": [["type_map", "get", "vertica_type"]]}, "params_p": {"args": [], "cls": [["list", 0.08515454948143533], ["bool", 0.07394119277931854], ["str", 0.07359367190858086]], "kwargs": [], "self": [], "vertica_type": [["str", 0.28820850650961827], ["Dict[str, Any]", 0.15851852753188828], ["Optional[type]", 0.09503833428831387], ["django.db.models.Model", 0.08680365426681474]]}, "q_name": "VerticaToHiveOperator.type_map", "ret_exprs": ["return type_map.get(vertica_type, \"STRING\")"], "ret_type": "", "ret_type_p": [["str", 0.08541163627295702]], "variables": {"type_map": ""}, "variables_p": {"type_map": [["Dict[str, str]", 0.39674956388103444], ["str", 0.32718952119343436], ["Dict[int, str]", 0.11702867313959565], ["Dict[Any, str]", 0.09590305742855762], ["Dict[str, int]", 0.06312918435737785]]}}, {"docstring": {"func": null, "long_descr": null, "ret": null}, "fn_lc": [[114, 4], [141, 13]], "fn_var_ln": {"col_position": [[126, 16], [126, 28]], "conn": [[119, 8], [119, 12]], "csv_writer": [[123, 12], [123, 22]], "cursor": [[120, 8], [120, 14]], "field_dict": [[124, 12], [124, 22]], "hive": [[115, 8], [115, 12]], "vertica": [[116, 8], [116, 15]]}, "fn_var_occur": {"col_position": [["col_position", "col_count"], ["field_dict", "col_position", "field", "field", "self", "type_map", "field"]], "conn": [["conn", "vertica", "get_conn"], ["cursor", "conn", "cursor"], ["conn", "close"]], "csv_writer": [["csv_writer", "csv", "writer", "f", "delimiter", "self", "delimiter"], ["csv_writer", "writerows", "cursor", "iterate"]], "cursor": [["cursor", "conn", "cursor"], ["cursor", "execute", "self", "sql"], ["enumerate", "cursor", "description", "start"], ["csv_writer", "writerows", "cursor", "iterate"], ["cursor", "close"]], "field_dict": [["field_dict", "OrderedDict"], ["field_dict", "col_position", "field", "field", "self", "type_map", "field"], ["hive", "load_file", "f", "name", "self", "hive_table", "field_dict", "field_dict", "create", "self", "create", "partition", "self", "partition", "delimiter", "self", "delimiter", "recreate", "self", "recreate"]], "hive": [["hive", "HiveCliHook", "hive_cli_conn_id", "self", "hive_cli_conn_id", "auth", "self", "hive_auth"], ["hive", "load_file", "f", "name", "self", "hive_table", "field_dict", "field_dict", "create", "self", "create", "partition", "self", "partition", "delimiter", "self", "delimiter", "recreate", "self", "recreate"]], "vertica": [["vertica", "VerticaHook", "vertica_conn_id", "self", "vertica_conn_id"], ["conn", "vertica", "get_conn"]]}, "name": "execute", "params": {"context": "airflow.utils.context.Context", "self": ""}, "params_descr": {"context": "", "self": ""}, "params_occur": {"context": [], "self": [["hive", "HiveCliHook", "hive_cli_conn_id", "self", "hive_cli_conn_id", "auth", "self", "hive_auth"], ["vertica", "VerticaHook", "vertica_conn_id", "self", "vertica_conn_id"], ["self", "log", "info"], ["cursor", "execute", "self", "sql"], ["csv_writer", "csv", "writer", "f", "delimiter", "self", "delimiter"], ["field_dict", "col_position", "field", "field", "self", "type_map", "field"], ["self", "log", "info"], ["hive", "load_file", "f", "name", "self", "hive_table", "field_dict", "field_dict", "create", "self", "create", "partition", "self", "partition", "delimiter", "self", "delimiter", "recreate", "self", "recreate"]]}, "params_p": {"args": [], "context": [["int", 0.19999999999999998], ["str", 0.19999999999999998], ["Iterable['Context']", 0.09999999999999999], ["dict", 0.09999999999999999], ["bool", 0.09999999999999999]], "kwargs": [], "self": []}, "q_name": "VerticaToHiveOperator.execute", "ret_exprs": [], "ret_type": "", "variables": {"col_position": "", "conn": "", "csv_writer": "", "cursor": "", "field_dict": "", "hive": "", "vertica": ""}, "variables_p": {"col_position": [["List[list]", 0.10487827816085155], ["dict", 0.09572689040894646], ["List[str]", 0.09229603308184438], ["list", 0.08804295940739702]], "conn": [["str", 0.2099570029337717], ["salon.models.StylistService", 0.08741393225280333]], "csv_writer": [["Counter[str]", 0.08718416284301628]], "cursor": [["str", 0.10790116474267336]], "field_dict": [["ddionrails.data.models.variable.Variable", 0.19829459028269464], ["OrderedDict", 0.09200277007260377]], "hive": [["str", 0.306393972450695], ["bool", 0.10204106469025624], ["float", 0.09087293051530619]], "vertica": [["dict", 0.2351502245983807], ["List[tuple]", 0.11878538430824558]]}}], "name": "VerticaToHiveOperator", "q_name": "VerticaToHiveOperator", "variables": {"template_ext": "typing.Sequence[builtins.str]", "template_fields": "typing.Sequence[builtins.str]", "template_fields_renderers": "", "ui_color": ""}, "variables_p": {"template_ext": [["str", 0.9999999999999999]], "template_fields": [["Tuple[str, str, str, str, str, str]", 0.2857142856828355], ["Tuple[str, str, str]", 0.2857142856828355], ["Tuple[str, str, str, str]", 0.2857142856828355], ["Tuple[str, str, str, str, str]", 0.14285714284141776], ["Dict[str, str]", 7.42502725571635e-11]], "template_fields_renderers": [["Tuple[str, str, str, str, str, str]", 0.2857142856828355], ["Tuple[str, str, str]", 0.2857142856828355], ["Tuple[str, str, str, str]", 0.2857142856828355], ["Tuple[str, str, str, str, str]", 0.14285714284141776], ["Dict[str, str]", 7.42502725571635e-11]], "ui_color": [["str", 0.4], ["List[str]", 0.1], ["int", 0.1], ["raiden.utils.WithdrawAmount", 0.1], ["Dict[str, List[Any]]", 0.1], ["Tuple[str, str, str, str, str, str, str, str]", 0.1]]}}], "funcs": [], "imports": ["__future__", "annotations", "csv", "collections", "OrderedDict", "tempfile", "NamedTemporaryFile", "typing", "TYPE_CHECKING", "Any", "Sequence", "airflow", "models", "BaseOperator", "airflow", "providers", "apache", "hive", "hooks", "hive", "HiveCliHook", "airflow", "providers", "vertica", "hooks", "vertica", "VerticaHook", "airflow", "utils", "context", "Context"], "mod_var_ln": {}, "mod_var_occur": {}, "no_types_annot": {"D": 5, "I": 0, "U": 23}, "session_id": "e4XH3UoVQGhZKoon-OkgXDpDR57fe_8IKBlKJZKmH9M", "set": null, "tc": [false, null], "type_annot_cove": 0.18, "typed_seq": "", "untyped_seq": "", "variables": {}, "variables_p": {}}}