{"error": null, "response": {"classes": [{"cls_lc": [[1, 0], [4, 24]], "cls_var_ln": {}, "cls_var_occur": {}, "funcs": [{"docstring": {"func": null, "long_descr": null, "ret": null}, "fn_lc": [[2, 4], [4, 24]], "fn_var_ln": {"next": [[4, 8], [4, 17]], "val": [[3, 8], [3, 16]]}, "fn_var_occur": {"next": [["self", "next", "None"]], "val": [["self", "val", "val"]]}, "name": "__init__", "params": {"self": "", "val": ""}, "params_descr": {"self": "", "val": ""}, "params_occur": {"self": [["self", "val", "val"], ["self", "next", "None"]], "val": [["self", "val", "val"]]}, "params_p": {"args": [], "kwargs": [], "self": [], "val": [["int", 0.3], ["bool", 0.09999999999999999], ["float", 0.09999999999999999]]}, "q_name": "Node.__init__", "ret_exprs": [], "ret_type": "", "variables": {"next": "", "val": ""}, "variables_p": {"next": [["\"Frame\"", 0.19999999999676038], ["str", 3.971941177518544e-12], ["Dict[str, Any]", 3.6175949269712212e-12]], "val": [["str", 0.30000000000000004], ["Dict[str, Any]", 0.1], ["dict", 0.1], ["int", 0.1]]}}], "name": "Node", "q_name": "Node", "variables": {}, "variables_p": {}}], "funcs": [{"docstring": {"func": "Time Complexity: O(N)", "long_descr": "Space Complexity: O(N)", "ret": null}, "fn_lc": [[6, 0], [19, 24]], "fn_var_ln": {"hashset": [[11, 4], [11, 11]], "head": [[19, 8], [19, 12]], "next": [[15, 12], [15, 21]], "prev": [[18, 12], [18, 16]]}, "fn_var_occur": {"hashset": [["hashset", "set"], ["head", "val", "hashset"], ["hashset", "add", "head", "val"]], "head": [["head", "val", "hashset"], ["prev", "next", "head", "next"], ["hashset", "add", "head", "val"], ["prev", "head"], ["head", "head", "next"]], "next": [["prev", "next", "head", "next"], ["head", "head", "next"]], "prev": [["prev", "Node"], ["prev", "next", "head", "next"], ["prev", "head"]]}, "name": "remove_dups", "params": {"head": ""}, "params_descr": {"head": ""}, "params_occur": {"head": [["head", "val", "hashset"], ["prev", "next", "head", "next"], ["hashset", "add", "head", "val"], ["prev", "head"], ["head", "head", "next"]]}, "params_p": {"args": [], "head": [["float", 0.14776646541882227], ["list", 0.13307237029246707]], "kwargs": []}, "q_name": "remove_dups", "ret_exprs": [], "ret_type": "", "variables": {"hashset": "", "head": "", "next": "", "prev": ""}, "variables_p": {"hashset": [["set", 0.46486813520847303], ["Set[str]", 0.16581208814369436], ["Tuple[Literal, Literal, Literal, Literal, Literal, Literal, Literal, Literal, Literal, Literal, Literal, Literal, Literal, Literal]", 0.09343639493126882], ["dict", 0.08516050569348596], ["Dict[str, Optional[str]]", 0.08443229632336406]], "head": [["Set[Tuple[Any, Any]]", 0.19570585252328776], ["Set[str]", 0.11291224692057386]], "next": [["int", 0.2], ["dict", 0.1], ["List[int]", 0.1], ["List[List[int]]", 0.1], ["str", 0.1]], "prev": [["int", 0.49999999998749156], ["list", 3.894300058824186e-12]]}}, {"docstring": {"func": "Time Complexity: O(N^2)", "long_descr": "Space Complexity: O(1)", "ret": null}, "fn_lc": [[21, 0], [34, 30]], "fn_var_ln": {"current": [[34, 8], [34, 15]], "next": [[31, 16], [31, 27]], "runner": [[33, 16], [33, 22]]}, "fn_var_occur": {"current": [["current", "head"], ["runner", "current"], ["runner", "next", "val", "current", "val"], ["current", "current", "next"]], "next": [["runner", "next"], ["runner", "next", "val", "current", "val"], ["runner", "next", "runner", "next", "next"], ["runner", "runner", "next"], ["current", "current", "next"]], "runner": [["runner", "current"], ["runner", "next"], ["runner", "next", "val", "current", "val"], ["runner", "next", "runner", "next", "next"], ["runner", "runner", "next"]]}, "name": "remove_dups_wothout_set", "params": {"head": ""}, "params_descr": {"head": ""}, "params_occur": {"head": [["current", "head"]]}, "params_p": {"args": [], "head": [["bool", 0.36481043217172715], ["int", 0.2561106669556916], ["float", 0.09120260804293179]], "kwargs": []}, "q_name": "remove_dups_wothout_set", "ret_exprs": [], "ret_type": "", "variables": {"current": "", "next": "", "runner": ""}, "variables_p": {"current": [["int", 0.2], ["dict", 0.1], ["List[int]", 0.1], ["List[List[int]]", 0.1], ["str", 0.1]], "next": [["int", 0.2], ["dict", 0.1], ["List[int]", 0.1], ["List[List[int]]", 0.1], ["str", 0.1]], "runner": [["int", 0.2], ["dict", 0.1], ["List[int]", 0.1], ["List[List[int]]", 0.1], ["str", 0.1]]}}, {"docstring": {"func": null, "long_descr": null, "ret": null}, "fn_lc": [[36, 0], [42, 17]], "fn_var_ln": {"head": [[40, 8], [40, 12]], "string": [[37, 4], [37, 10]]}, "fn_var_occur": {"head": [["head", "next"], ["string", "head", "val"], ["head", "head", "next"], ["string", "head", "val"]], "string": [["string", "head", "val"], ["string", "head", "val"], ["print", "string"]]}, "name": "print_linked_list", "params": {"head": ""}, "params_descr": {"head": ""}, "params_occur": {"head": [["head", "next"], ["string", "head", "val"], ["head", "head", "next"], ["string", "head", "val"]]}, "params_p": {"args": [], "head": [["str", 0.7894782893371827], ["Optional[str]", 0.12661552084981575]], "kwargs": []}, "q_name": "print_linked_list", "ret_exprs": [], "ret_type": "", "variables": {"head": "", "string": ""}, "variables_p": {"head": [["str", 0.3706487878446621], ["list", 0.3368877095827311], ["List[str]", 0.0663484115182113]], "string": [["str", 1.0]]}}], "imports": [], "mod_var_ln": {"a1": [[46, 0], [46, 2]], "a2": [[47, 0], [47, 2]], "b": [[48, 0], [48, 1]], "c1": [[49, 0], [49, 2]], "c2": [[51, 0], [51, 2]], "d": [[50, 0], [50, 1]], "f": [[52, 0], [52, 1]], "g": [[53, 0], [53, 1]], "next": [[61, 0], [61, 6]]}, "mod_var_occur": {"a1": [["a1", "next", "a2"], ["remove_dups", "a1"], ["print_linked_list", "a1"], ["remove_dups_wothout_set", "a1"], ["print_linked_list", "a1"]], "a2": [["a1", "next", "a2"], ["a2", "next", "b"]], "b": [["a2", "next", "b"], ["b", "next", "c1"]], "c1": [["b", "next", "c1"], ["c1", "next", "d"]], "c2": [["d", "next", "c2"], ["c2", "next", "f"]], "d": [["c1", "next", "d"], ["d", "next", "c2"]], "f": [["c2", "next", "f"], ["f", "next", "g"]], "g": [["f", "next", "g"]], "next": []}, "no_types_annot": {"D": 0, "I": 0, "U": 25}, "session_id": "E4DUJp92vkT4_u_zivJMAQR4mUo96nwNcytmbQ7_BvM", "set": null, "tc": [false, null], "type_annot_cove": 0.0, "typed_seq": "", "untyped_seq": "", "variables": {"a1": "", "a2": "", "b": "", "c1": "", "c2": "", "d": "", "f": "", "g": "", "next": ""}, "variables_p": {"a1": [["list", 0.7427323569381983]], "a2": [["List[float]", 0.21001333424690394], ["int", 0.0966323846562643], ["str", 0.0966323846562643]], "b": [["Pattern[str]", 0.29570136759761534], ["str", 0.2880529417484522], ["int", 0.10648408956553146], ["float", 0.10443616736519219]], "c1": [["str", 0.19203786408831186], ["Dict[str, Union[Any, str]]", 0.13198424957601623], ["List[Union[Any, int]]", 0.08782815811331347], ["frozenset[str]", 0.08410537014629621]], "c2": [["str", 0.23081471163762393], ["Type[List[Any]]", 0.09943877647449811], ["List[str]", 0.09943877647449811], ["int", 0.09431491824957827], ["List[Union[Any, int]]", 0.09309439221575033]], "d": [["float", 0.1697904774701642], ["List[bytes]", 0.08173689880917827]], "f": [["float", 0.5642284728720466], ["str", 0.08282529152995759]], "g": [["int", 0.2], ["dict", 0.1], ["List[int]", 0.1], ["List[List[int]]", 0.1], ["str", 0.1]], "next": [["str", 0.4], ["List[str]", 0.1], ["int", 0.1], ["Dict[str, List[Any]]", 0.1], ["Tuple[str, str, str, str, str, str, str, str]", 0.1]]}}}