{"error": null, "response": {"classes": [{"cls_lc": [[81, 4], [83, 16]], "cls_var_ln": {}, "cls_var_occur": {}, "funcs": [{"docstring": {"func": null, "long_descr": null, "ret": null}, "fn_lc": [[82, 8], [83, 16]], "fn_var_ln": {}, "fn_var_occur": {}, "name": "__init__", "params": {"kwargs": "", "self": ""}, "params_descr": {"kwargs": "", "self": ""}, "params_occur": {"kwargs": [], "self": []}, "params_p": {"args": [], "kwargs": [], "self": []}, "q_name": "Client.__init__", "ret_exprs": [], "ret_type": "", "variables": {}, "variables_p": {}}], "name": "Client", "q_name": "docker.Client", "variables": {}, "variables_p": {}}, {"cls_lc": [[108, 0], [114, 12]], "cls_var_ln": {}, "cls_var_occur": {}, "funcs": [{"docstring": {"func": null, "long_descr": null, "ret": null}, "fn_lc": [[110, 4], [111, 26]], "fn_var_ln": {"debug": [[111, 8], [111, 18]]}, "fn_var_occur": {"debug": [["self", "debug", "False"]]}, "name": "__init__", "params": {"self": ""}, "params_descr": {"self": ""}, "params_occur": {"self": [["self", "debug", "False"]]}, "params_p": {"args": [], "kwargs": [], "self": []}, "q_name": "DockerBaseClass.__init__", "ret_exprs": [], "ret_type": "", "variables": {"debug": ""}, "variables_p": {"debug": [["str", 0.6764829690625138], ["Union[Literal, str]", 0.22225043558443883], ["Union[Literal[False], str]", 0.10126659535304741]]}}, {"docstring": {"func": null, "long_descr": null, "ret": null}, "fn_lc": [[113, 4], [114, 12]], "fn_var_ln": {}, "fn_var_occur": {}, "name": "log", "params": {"msg": "", "pretty_print": "", "self": ""}, "params_descr": {"msg": "", "pretty_print": "", "self": ""}, "params_occur": {"msg": [], "pretty_print": [], "self": []}, "params_p": {"args": [], "kwargs": [], "msg": [["str", 0.9999996484063297], ["Callable", 1.1710867763372246e-07]], "pretty_print": [["str", 0.9999996484063297], ["Callable", 1.1710867763372246e-07]], "self": []}, "q_name": "DockerBaseClass.log", "ret_exprs": [], "ret_type": "", "variables": {}, "variables_p": {}}], "name": "DockerBaseClass", "q_name": "DockerBaseClass", "variables": {}, "variables_p": {}}, {"cls_lc": [[124, 0], [462, 41]], "cls_var_ln": {}, "cls_var_occur": {}, "funcs": [{"docstring": {"func": null, "long_descr": null, "ret": null}, "fn_lc": [[126, 4], [168, 51]], "fn_var_ln": {"_connect_params": [[161, 8], [161, 28]], "arg_spec": [[133, 12], [133, 25]], "check_mode": [[160, 8], [160, 23]], "debug": [[159, 8], [159, 18]], "merged_arg_spec": [[129, 8], [129, 23]], "module": [[145, 8], [145, 19]], "mutually_exclusive_params": [[135, 8], [135, 33]], "required_together_params": [[140, 8], [140, 32]]}, "fn_var_occur": {"_connect_params": [["self", "_connect_params", "self", "_get_connect_params"], ["super", "AnsibleDockerClient", "self", "__init__", "self", "_connect_params"]], "arg_spec": [["self", "arg_spec", "merged_arg_spec"]], "check_mode": [["self", "check_mode", "self", "module", "check_mode"]], "debug": [["self", "debug", "self", "module", "params", "get"]], "merged_arg_spec": [["merged_arg_spec", "dict"], ["merged_arg_spec", "update", "DOCKER_COMMON_ARGS"], ["merged_arg_spec", "update", "argument_spec"], ["self", "arg_spec", "merged_arg_spec"], ["self", "module", "AnsibleModule", "argument_spec", "merged_arg_spec", "supports_check_mode", "supports_check_mode", "mutually_exclusive", "mutually_exclusive_params", "required_together", "required_together_params", "required_if", "required_if"]], "module": [["self", "module", "AnsibleModule", "argument_spec", "merged_arg_spec", "supports_check_mode", "supports_check_mode", "mutually_exclusive", "mutually_exclusive_params", "required_together", "required_together_params", "required_if", "required_if"], ["self", "debug", "self", "module", "params", "get"], ["self", "check_mode", "self", "module", "check_mode"]], "mutually_exclusive_params": [["mutually_exclusive_params", "DOCKER_MUTUALLY_EXCLUSIVE"], ["mutually_exclusive_params", "mutually_exclusive"], ["self", "module", "AnsibleModule", "argument_spec", "merged_arg_spec", "supports_check_mode", "supports_check_mode", "mutually_exclusive", "mutually_exclusive_params", "required_together", "required_together_params", "required_if", "required_if"]], "required_together_params": [["required_together_params", "DOCKER_REQUIRED_TOGETHER"], ["required_together_params", "required_together"], ["self", "module", "AnsibleModule", "argument_spec", "merged_arg_spec", "supports_check_mode", "supports_check_mode", "mutually_exclusive", "mutually_exclusive_params", "required_together", "required_together_params", "required_if", "required_if"]]}, "name": "__init__", "params": {"argument_spec": "", "mutually_exclusive": "", "required_if": "", "required_together": "", "self": "", "supports_check_mode": ""}, "params_descr": {"argument_spec": "", "mutually_exclusive": "", "required_if": "", "required_together": "", "self": "", "supports_check_mode": ""}, "params_occur": {"argument_spec": [["merged_arg_spec", "update", "argument_spec"], ["self", "module", "AnsibleModule", "argument_spec", "merged_arg_spec", "supports_check_mode", "supports_check_mode", "mutually_exclusive", "mutually_exclusive_params", "required_together", "required_together_params", "required_if", "required_if"]], "mutually_exclusive": [["mutually_exclusive_params", "mutually_exclusive"], ["self", "module", "AnsibleModule", "argument_spec", "merged_arg_spec", "supports_check_mode", "supports_check_mode", "mutually_exclusive", "mutually_exclusive_params", "required_together", "required_together_params", "required_if", "required_if"]], "required_if": [["self", "module", "AnsibleModule", "argument_spec", "merged_arg_spec", "supports_check_mode", "supports_check_mode", "mutually_exclusive", "mutually_exclusive_params", "required_together", "required_together_params", "required_if", "required_if"]], "required_together": [["required_together_params", "required_together"], ["self", "module", "AnsibleModule", "argument_spec", "merged_arg_spec", "supports_check_mode", "supports_check_mode", "mutually_exclusive", "mutually_exclusive_params", "required_together", "required_together_params", "required_if", "required_if"]], "self": [["self", "arg_spec", "merged_arg_spec"], ["self", "module", "AnsibleModule", "argument_spec", "merged_arg_spec", "supports_check_mode", "supports_check_mode", "mutually_exclusive", "mutually_exclusive_params", "required_together", "required_together_params", "required_if", "required_if"], ["self", "fail", "HAS_DOCKER_ERROR"], ["self", "fail", "docker_version", "MIN_DOCKER_VERSION"], ["self", "debug", "self", "module", "params", "get"], ["self", "check_mode", "self", "module", "check_mode"], ["self", "_connect_params", "self", "_get_connect_params"], ["super", "AnsibleDockerClient", "self", "__init__", "self", "_connect_params"], ["self", "fail", "exc"], ["self", "fail", "exc"]], "supports_check_mode": [["self", "module", "AnsibleModule", "argument_spec", "merged_arg_spec", "supports_check_mode", "supports_check_mode", "mutually_exclusive", "mutually_exclusive_params", "required_together", "required_together_params", "required_if", "required_if"]]}, "params_p": {"args": [], "argument_spec": [["bool", 0.1937214541370425], ["str", 0.15928389246033808], ["float", 0.0793187527926027]], "kwargs": [], "mutually_exclusive": [["int", 0.3835898977368598], ["str", 0.27448774407099175], ["bool", 0.10065861494007444]], "required_if": [["str", 0.2099351650209008], ["bool", 0.10451980103085808], ["Iterable[str]", 0.10136358416183765], ["float", 0.09143090769540667], ["Optional[str]", 0.09143090769540667], ["List[Tuple[str, str]]", 0.09143090769540667], ["list", 0.0889900604239314]], "required_together": [["int", 0.3072374252390636], ["List[str]", 0.21587189556924902], ["str", 0.10793594778462451], ["bool", 0.0994614456413947], ["Optional[str]", 0.09278273955450422]], "self": [], "supports_check_mode": [["str", 0.2099351650209008], ["bool", 0.10451980103085808], ["Iterable[str]", 0.10136358416183765], ["float", 0.09143090769540667], ["Optional[str]", 0.09143090769540667], ["List[Tuple[str, str]]", 0.09143090769540667], ["list", 0.0889900604239314]]}, "q_name": "AnsibleDockerClient.__init__", "ret_exprs": [], "ret_type": "", "variables": {"_connect_params": "", "arg_spec": "", "check_mode": "", "debug": "", "merged_arg_spec": "", "module": "", "mutually_exclusive_params": "", "required_together_params": ""}, "variables_p": {"_connect_params": [["str", 0.2597358217260568], ["int", 0.24985267587143206], ["Dict[int, str]", 0.11909850821177122], ["bytes", 0.10390592900890418], ["Dict[str, Union[int, str, Any, Any]]", 0.09708578722700534], ["Pattern[str]", 0.083636002414546]], "arg_spec": [["str", 0.30000000000000004], ["Dict[str, Any]", 0.1], ["dict", 0.1], ["int", 0.1]], "check_mode": [["str", 0.3375133376851068], ["List[str]", 0.19821938613340184], ["Dict[Any, str]", 0.19021248745565933], ["Tuple[str, str, str, str, str, str]", 0.09496707142358705], ["Dict[str, str]", 0.09086594636289667], ["Set[str]", 0.08822177093934848]], "debug": [["int", 0.38642371874613024], ["str", 0.2992512310450093], ["bool", 0.09660592968653256]], "merged_arg_spec": [["requests.adapters.HTTPAdapter", 0.22135768125155814], ["str", 0.08819265388865867], ["Final[Dict[str, Any]]", 0.08504122349246065]], "module": [["property", 0.24087755739379907]], "mutually_exclusive_params": [], "required_together_params": [["dict", 0.09234715543910116]]}}, {"docstring": {"func": null, "long_descr": null, "ret": null}, "fn_lc": [[170, 4], [171, 12]], "fn_var_ln": {}, "fn_var_occur": {}, "name": "log", "params": {"msg": "", "pretty_print": "", "self": ""}, "params_descr": {"msg": "", "pretty_print": "", "self": ""}, "params_occur": {"msg": [], "pretty_print": [], "self": []}, "params_p": {"args": [], "kwargs": [], "msg": [["str", 0.9999996484063297], ["Callable", 1.1710867763372246e-07]], "pretty_print": [["str", 0.9999996484063297], ["Callable", 1.1710867763372246e-07]], "self": []}, "q_name": "AnsibleDockerClient.log", "ret_exprs": [], "ret_type": "", "variables": {}, "variables_p": {}}, {"docstring": {"func": null, "long_descr": null, "ret": null}, "fn_lc": [[180, 4], [181, 38]], "fn_var_ln": {}, "fn_var_occur": {}, "name": "fail", "params": {"msg": "", "self": ""}, "params_descr": {"msg": "", "self": ""}, "params_occur": {"msg": [["self", "module", "fail_json", "msg", "msg"]], "self": [["self", "module", "fail_json", "msg", "msg"]]}, "params_p": {"args": [], "kwargs": [], "msg": [["str", 0.4000000000000001], ["List[str]", 0.10000000000000002], ["bytes", 0.10000000000000002], ["hackathon.utils.utils.DataMessage", 0.10000000000000002]], "self": []}, "q_name": "AnsibleDockerClient.fail", "ret_exprs": [], "ret_type": "", "variables": {}, "variables_p": {}}, {"docstring": {"func": null, "long_descr": null, "ret": null}, "fn_lc": [[184, 4], [210, 28]], "fn_var_ln": {"env_value": [[194, 12], [194, 21]]}, "fn_var_occur": {"env_value": [["env_value", "os", "environ", "get", "env_variable"], ["env_value", "None"], ["os", "path", "join", "env_value"], ["os", "path", "join", "env_value"], ["os", "path", "join", "env_value"], ["env_value", "BOOLEANS_TRUE"], ["env_value", "BOOLEANS_FALSE"]]}, "name": "_get_value", "params": {"default_value": "", "env_variable": "", "param_name": "", "param_value": ""}, "params_descr": {"default_value": "", "env_variable": "", "param_name": "", "param_value": ""}, "params_occur": {"default_value": [], "env_variable": [["env_variable", "None"], ["env_value", "os", "environ", "get", "env_variable"]], "param_name": [], "param_value": [["param_value", "None"], ["param_value", "BOOLEANS_TRUE"], ["param_value", "BOOLEANS_FALSE"]]}, "params_p": {"args": [], "default_value": [["str", 0.8397031201442984], ["Iterable[str]", 0.08163918850776332], ["bool", 0.07865769134793842]], "env_variable": [["str", 0.48388637726500155], ["Optional[str]", 0.4198689674685424], ["Tuple[str]", 0.09624465526645598]], "kwargs": [], "param_name": [["str", 0.8397031201442984], ["Iterable[str]", 0.08163918850776332], ["bool", 0.07865769134793842]], "param_value": [["Optional[bool]", 0.3303196924963911], ["Optional[float]", 0.12045305126734883], ["Optional[Union[str, Any]]", 0.11093123961751557], ["Optional[\"ValidatorTypes\"]", 0.09939500799078373], ["Optional[str]", 0.08230562222943223], ["bool", 0.0811599702831459]], "self": []}, "q_name": "AnsibleDockerClient._get_value", "ret_exprs": ["return True", "return False", "return param_value", "return os.path.join(env_value, 'cert.pem')", "return os.path.join(env_value, 'ca.pem')", "return os.path.join(env_value, 'key.pem')", "return True", "return False", "return env_value", "return default_value"], "ret_type": "", "ret_type_p": [["bool", 0.9999999999999999]], "variables": {"env_value": ""}, "variables_p": {"env_value": [["str", 0.7699671038443726], ["Dict[str, str]", 0.11328436631145405]]}}, {"docstring": {"func": null, "long_descr": null, "ret": null}, "fn_lc": [[213, 4], [257, 21]], "fn_var_ln": {"params": [[219, 8], [219, 14]], "parsed_url": [[251, 12], [251, 22]], "result": [[231, 8], [231, 14]], "use_tls": [[225, 12], [225, 19]]}, "fn_var_occur": {"params": [["params", "dict"], ["params", "key", "self", "module", "params", "get", "key"], ["self", "module", "params", "get"], ["use_tls", "self", "module", "params", "get"], ["params", "True"], ["params", "True"], ["result", "dict", "docker_host", "self", "_get_value", "params", "DEFAULT_DOCKER_HOST", "tls_hostname", "self", "_get_value", "params", "api_version", "self", "_get_value", "params", "cacert_path", "self", "_get_value", "params", "None", "cert_path", "self", "_get_value", "params", "None", "key_path", "self", "_get_value", "params", "None", "ssl_version", "self", "_get_value", "params", "None", "tls", "self", "_get_value", "params", "DEFAULT_TLS", "tls_verify", "self", "_get_value", "params", "DEFAULT_TLS_VERIFY", "timeout", "self", "_get_value", "params", "DEFAULT_TIMEOUT_SECONDS"]], "parsed_url": [["parsed_url", "urlparse", "result"], ["parsed_url", "netloc"], ["result", "parsed_url", "netloc", "parsed_url", "netloc", "rindex"], ["result", "parsed_url"]], "result": [["result", "dict", "docker_host", "self", "_get_value", "params", "DEFAULT_DOCKER_HOST", "tls_hostname", "self", "_get_value", "params", "api_version", "self", "_get_value", "params", "cacert_path", "self", "_get_value", "params", "None", "cert_path", "self", "_get_value", "params", "None", "key_path", "self", "_get_value", "params", "None", "ssl_version", "self", "_get_value", "params", "None", "tls", "self", "_get_value", "params", "DEFAULT_TLS", "tls_verify", "self", "_get_value", "params", "DEFAULT_TLS_VERIFY", "timeout", "self", "_get_value", "params", "DEFAULT_TIMEOUT_SECONDS"], ["result", "None"], ["parsed_url", "urlparse", "result"], ["result", "parsed_url", "netloc", "parsed_url", "netloc", "rindex"], ["result", "parsed_url"]], "use_tls": [["use_tls", "self", "module", "params", "get"]]}, "name": "auth_params", "params": {"self": ""}, "params_descr": {"self": ""}, "params_occur": {"self": [["self", "log"], ["params", "key", "self", "module", "params", "get", "key"], ["self", "module", "params", "get"], ["use_tls", "self", "module", "params", "get"], ["result", "dict", "docker_host", "self", "_get_value", "params", "DEFAULT_DOCKER_HOST", "tls_hostname", "self", "_get_value", "params", "api_version", "self", "_get_value", "params", "cacert_path", "self", "_get_value", "params", "None", "cert_path", "self", "_get_value", "params", "None", "key_path", "self", "_get_value", "params", "None", "ssl_version", "self", "_get_value", "params", "None", "tls", "self", "_get_value", "params", "DEFAULT_TLS", "tls_verify", "self", "_get_value", "params", "DEFAULT_TLS_VERIFY", "timeout", "self", "_get_value", "params", "DEFAULT_TIMEOUT_SECONDS"]]}, "params_p": {"args": [], "kwargs": [], "self": []}, "q_name": "AnsibleDockerClient.auth_params", "ret_exprs": ["return result"], "ret_type": "", "ret_type_p": [["bool", 0.11709024714250515], ["List[object]", 0.08844690477531908], ["str", 0.08795422118059903]], "variables": {"params": "", "parsed_url": "", "result": "", "use_tls": ""}, "variables_p": {"params": [["dict", 1.0000000000000002]], "parsed_url": [["str", 0.383325324145062], ["Dict[str, str]", 0.12165392574054132]], "result": [["str", 0.2681811047036029], ["Dict[str, Any]", 0.08281648025130563]], "use_tls": [["bool", 0.20817113506825002], ["str", 0.18326222200092804], ["dict", 0.1294791481450663], ["Dict[str, str]", 0.10176639937098647], ["utils.MinMaxStats", 0.09931073861488168], ["int", 0.09337010868113373]]}}, {"docstring": {"func": null, "long_descr": null, "ret": null}, "fn_lc": [[259, 4], [267, 50]], "fn_var_ln": {"tls_config": [[264, 12], [264, 22]]}, "fn_var_occur": {"tls_config": [["tls_config", "TLSConfig", "kwargs"]]}, "name": "_get_tls_config", "params": {"kwargs": "", "self": ""}, "params_descr": {"kwargs": "", "self": ""}, "params_occur": {"kwargs": [["self", "log", "key", "kwargs", "key"], ["tls_config", "TLSConfig", "kwargs"]], "self": [["self", "log"], ["self", "log", "key", "kwargs", "key"], ["self", "fail", "exc"]]}, "params_p": {"args": [], "kwargs": [], "self": []}, "q_name": "AnsibleDockerClient._get_tls_config", "ret_exprs": ["return tls_config"], "ret_type": "", "ret_type_p": [["Dict[str, Any]", 0.21879939006486193], ["raiden.constants.Environment", 0.09664242548602313], ["cmk.utils.type_defs.OptionalConfigSerial", 0.0957399939532222], ["List[str]", 0.08667950976225611], ["bool", 0.08255335485078334], ["str", 0.0801327670863592], ["dict", 0.0799217516883681]], "variables": {"tls_config": ""}, "variables_p": {"tls_config": [["Dict[str, Optional[str]]", 0.3858483624387263], ["str", 0.17556457183031685], ["Dict[str, Union[Any, Any]]", 0.10848532793307541], ["Dict[str, int]", 0.06791191134389889], ["Dict[str, Union[Any, Any, Any, Any, Any]]", 0.06068149818312381], ["Dict[str, Dict[str, str]]", 0.055950890403168016]]}}, {"docstring": {"func": null, "long_descr": null, "ret": null}, "fn_lc": [[269, 4], [340, 44]], "fn_var_ln": {"auth": [[270, 8], [270, 12]], "tls_config": [[330, 12], [330, 22]]}, "fn_var_occur": {"auth": [["auth", "self", "auth_params"], ["self", "log", "key", "auth", "key"], ["auth", "auth"], ["auth", "auth", "replace"], ["auth", "auth", "auth"], ["tls_config", "self", "_get_tls_config", "client_cert", "auth", "auth", "verify", "False", "ssl_version", "auth"], ["dict", "base_url", "auth", "tls", "tls_config", "version", "auth", "timeout", "auth"], ["tls_config", "self", "_get_tls_config", "verify", "False", "ssl_version", "auth"], ["dict", "base_url", "auth", "tls", "tls_config", "version", "auth", "timeout", "auth"], ["auth", "auth", "auth"], ["tls_config", "self", "_get_tls_config", "client_cert", "auth", "auth", "ca_cert", "auth", "verify", "True", "assert_hostname", "auth", "ssl_version", "auth"], ["tls_config", "self", "_get_tls_config", "client_cert", "auth", "auth", "verify", "True", "assert_hostname", "auth", "ssl_version", "auth"], ["dict", "base_url", "auth", "tls", "tls_config", "version", "auth", "timeout", "auth"], ["auth", "auth"], ["tls_config", "self", "_get_tls_config", "ca_cert", "auth", "assert_hostname", "auth", "verify", "True", "ssl_version", "auth"], ["dict", "base_url", "auth", "tls", "tls_config", "version", "auth", "timeout", "auth"], ["tls_config", "self", "_get_tls_config", "verify", "True", "assert_hostname", "auth", "ssl_version", "auth"], ["dict", "base_url", "auth", "tls", "tls_config", "version", "auth", "timeout", "auth"], ["dict", "base_url", "auth", "version", "auth", "timeout", "auth"]], "tls_config": [["tls_config", "self", "_get_tls_config", "client_cert", "auth", "auth", "verify", "False", "ssl_version", "auth"], ["dict", "base_url", "auth", "tls", "tls_config", "version", "auth", "timeout", "auth"], ["tls_config", "self", "_get_tls_config", "verify", "False", "ssl_version", "auth"], ["dict", "base_url", "auth", "tls", "tls_config", "version", "auth", "timeout", "auth"], ["tls_config", "self", "_get_tls_config", "client_cert", "auth", "auth", "ca_cert", "auth", "verify", "True", "assert_hostname", "auth", "ssl_version", "auth"], ["tls_config", "self", "_get_tls_config", "client_cert", "auth", "auth", "verify", "True", "assert_hostname", "auth", "ssl_version", "auth"], ["dict", "base_url", "auth", "tls", "tls_config", "version", "auth", "timeout", "auth"], ["tls_config", "self", "_get_tls_config", "ca_cert", "auth", "assert_hostname", "auth", "verify", "True", "ssl_version", "auth"], ["dict", "base_url", "auth", "tls", "tls_config", "version", "auth", "timeout", "auth"], ["tls_config", "self", "_get_tls_config", "verify", "True", "assert_hostname", "auth", "ssl_version", "auth"], ["dict", "base_url", "auth", "tls", "tls_config", "version", "auth", "timeout", "auth"]]}, "name": "_get_connect_params", "params": {"self": ""}, "params_descr": {"self": ""}, "params_occur": {"self": [["auth", "self", "auth_params"], ["self", "log"], ["self", "log", "key", "auth", "key"], ["tls_config", "self", "_get_tls_config", "client_cert", "auth", "auth", "verify", "False", "ssl_version", "auth"], ["tls_config", "self", "_get_tls_config", "verify", "False", "ssl_version", "auth"], ["tls_config", "self", "_get_tls_config", "client_cert", "auth", "auth", "ca_cert", "auth", "verify", "True", "assert_hostname", "auth", "ssl_version", "auth"], ["tls_config", "self", "_get_tls_config", "client_cert", "auth", "auth", "verify", "True", "assert_hostname", "auth", "ssl_version", "auth"], ["tls_config", "self", "_get_tls_config", "ca_cert", "auth", "assert_hostname", "auth", "verify", "True", "ssl_version", "auth"], ["tls_config", "self", "_get_tls_config", "verify", "True", "assert_hostname", "auth", "ssl_version", "auth"]]}, "params_p": {"args": [], "kwargs": [], "self": []}, "q_name": "AnsibleDockerClient._get_connect_params", "ret_exprs": ["return dict(base_url=auth['docker_host'], tls=tls_config, version=auth['api_version'], timeout=auth['timeout'])", "return dict(base_url=auth['docker_host'], tls=tls_config, version=auth['api_version'], timeout=auth['timeout'])", "return dict(base_url=auth['docker_host'], tls=tls_config, version=auth['api_version'], timeout=auth['timeout'])", "return dict(base_url=auth['docker_host'], tls=tls_config, version=auth['api_version'], timeout=auth['timeout'])", "return dict(base_url=auth['docker_host'], tls=tls_config, version=auth['api_version'], timeout=auth['timeout'])", "return dict(base_url=auth['docker_host'], version=auth['api_version'], timeout=auth['timeout'])"], "ret_type": "", "ret_type_p": [["str", 0.1374244472637153], ["int", 0.08278881054812057], ["apistar.types.WSGIEnviron", 0.07358126244278702], ["Exception", 0.06967441694458189]], "variables": {"auth": "", "tls_config": ""}, "variables_p": {"auth": [["str", 0.29495688979742274], ["Iterator[str]", 0.12712622787685315], ["MutableMapping[str, Any]", 0.09146114019181553], ["List[str]", 0.08160697311917608]], "tls_config": [["dict", 0.704027297232382], ["Dict[str, Union[Any, int]]", 0.08359021491263112], ["Dict[int, List[Any]]", 0.06900384016069]]}}, {"docstring": {"func": null, "long_descr": null, "ret": null}, "fn_lc": [[342, 4], [350, 48]], "fn_var_ln": {"match": [[343, 8], [343, 13]], "msg": [[345, 12], [345, 15]]}, "fn_var_occur": {"match": [["match", "re", "match", "str", "error"], ["msg", "self", "auth_params", "match", "group"]], "msg": [["msg", "self", "auth_params", "match", "group"], ["self", "fail", "msg"]]}, "name": "_handle_ssl_error", "params": {"error": "", "self": ""}, "params_descr": {"error": "", "self": ""}, "params_occur": {"error": [["match", "re", "match", "str", "error"], ["self", "fail", "error"]], "self": [["msg", "self", "auth_params", "match", "group"], ["self", "fail", "msg"], ["self", "fail", "error"]]}, "params_p": {"args": [], "error": [["bytes", 0.20599725947025574], ["T", 0.10090940884777244], ["errors.Error", 0.09967285103750795], ["Type", 0.0867861201139594]], "kwargs": [], "self": []}, "q_name": "AnsibleDockerClient._handle_ssl_error", "ret_exprs": [], "ret_type": "", "variables": {"match": "", "msg": ""}, "variables_p": {"match": [["Pattern[str]", 0.5559058956279253], ["Optional[Match[str]]", 0.4440941043720746]], "msg": [["int", 0.23616719733541874], ["dict", 0.17953229642307117], ["str", 0.16548059075942], ["Dict[Any, Dict[str, str]]", 0.11277789492485303], ["Dict[str, str]", 0.10116092854267264], ["Set[str]", 0.09579265916022765]]}}, {"docstring": {"func": "Lookup a container and return the inspection results.", "long_descr": null, "ret": null}, "fn_lc": [[352, 4], [389, 21]], "fn_var_ln": {"result": [[384, 16], [384, 22]], "search_name": [[361, 12], [361, 23]]}, "fn_var_occur": {"result": [["result", "None"], ["result", "container"], ["result", "container"], ["result", "container"], ["result", "None"], ["self", "log", "result"], ["result", "self", "inspect_container", "container", "result"]], "search_name": [["search_name", "name"], ["search_name", "name"], ["search_name", "container"]]}, "name": "get_container", "params": {"name": "", "self": ""}, "params_descr": {"name": "", "self": ""}, "params_occur": {"name": [["name", "None"], ["search_name", "name"], ["name", "startswith"], ["search_name", "name"], ["container", "startswith", "name"], ["container", "name"]], "self": [["self", "containers", "all", "True"], ["self", "log", "container"], ["self", "_handle_ssl_error", "exc"], ["self", "fail", "exc"], ["self", "log", "result"], ["result", "self", "inspect_container", "container", "result"], ["self", "log"], ["self", "fail", "exc"]]}, "params_p": {"args": [], "kwargs": [], "name": [["str", 0.5848319832414985], ["Optional[str]", 0.41516801675850135]], "self": []}, "q_name": "AnsibleDockerClient.get_container", "ret_exprs": ["return None", "return result"], "ret_type": "", "ret_type_p": [["Optional[str]", 0.42087361020495173], ["Optional[Type[Exception]]", 0.09327547854709772], ["str", 0.0863992283531392], ["int", 0.0863992283531392]], "variables": {"result": "", "search_name": ""}, "variables_p": {"result": [["list", 0.23700974222614857], ["Dict[str, str]", 0.0857508555001491], ["TypeError", 0.08420247399540307]], "search_name": [["Final", 0.5792056579739309], ["str", 0.21317806993603658], ["List[str]", 0.10658034037851839], ["Tuple[Literal, Literal]", 0.10103593171151412]]}}, {"docstring": {"func": "Lookup an image and return the inspection results.", "long_descr": null, "ret": null}, "fn_lc": [[391, 4], [420, 19]], "fn_var_ln": {"images": [[407, 16], [407, 22]], "inspection": [[414, 16], [414, 26]], "lookup": [[405, 16], [405, 22]], "registry": [[402, 12], [402, 20]], "repo_name": [[402, 22], [402, 31]]}, "fn_var_occur": {"images": [["images", "self", "_image_lookup", "name", "tag"], ["len", "images"], ["images", "self", "_image_lookup", "lookup", "tag"], ["len", "images"], ["len", "images"], ["inspection", "self", "inspect_image", "images"]], "inspection": [["inspection", "self", "inspect_image", "images"]], "lookup": [["lookup", "name"], ["self", "log", "lookup"], ["images", "self", "_image_lookup", "lookup", "tag"]], "registry": [["registry", "repo_name", "auth", "resolve_repository_name", "name"]], "repo_name": [["registry", "repo_name", "auth", "resolve_repository_name", "name"]]}, "name": "find_image", "params": {"name": "", "self": "", "tag": ""}, "params_descr": {"name": "", "self": "", "tag": ""}, "params_occur": {"name": [["self", "log", "name", "tag"], ["images", "self", "_image_lookup", "name", "tag"], ["registry", "repo_name", "auth", "resolve_repository_name", "name"], ["lookup", "name"], ["self", "fail", "name", "tag"], ["self", "fail", "name", "tag", "str", "exc"], ["self", "log", "name", "tag"]], "self": [["self", "log", "name", "tag"], ["images", "self", "_image_lookup", "name", "tag"], ["self", "log", "lookup"], ["images", "self", "_image_lookup", "lookup", "tag"], ["self", "fail", "name", "tag"], ["inspection", "self", "inspect_image", "images"], ["self", "fail", "name", "tag", "str", "exc"], ["self", "log", "name", "tag"]], "tag": [["self", "log", "name", "tag"], ["images", "self", "_image_lookup", "name", "tag"], ["images", "self", "_image_lookup", "lookup", "tag"], ["self", "fail", "name", "tag"], ["self", "fail", "name", "tag", "str", "exc"], ["self", "log", "name", "tag"]]}, "params_p": {"args": [], "kwargs": [], "name": [["str", 0.39602773720046686], ["Optional[str]", 0.21304689322076362], ["type", 0.09953290612841863], ["Optional[List[str]]", 0.0930281175680084]], "self": [], "tag": [["Optional[str]", 0.349416428384264], ["Optional[List[str]]", 0.1273868836991326], ["str", 0.12394585546970915], ["Optional[Dict[str, Any]]", 0.08666621496748189]]}, "q_name": "AnsibleDockerClient.find_image", "ret_exprs": ["return None", "return inspection", "return None"], "ret_type": "", "ret_type_p": [["Optional[str]", 0.5235470701962713], ["bool", 0.1765294534500578], ["Optional[float]", 0.10385378594182133]], "variables": {"images": "", "inspection": "", "lookup": "", "registry": "", "repo_name": ""}, "variables_p": {"images": [["list", 0.2983485552536185], ["int", 0.16775479110618913], ["List[str]", 0.11702323747944335], ["str", 0.11314723340416157], ["List[int]", 0.11171487560112962], ["Tuple[Literal]", 0.10452530204200781]], "inspection": [["int", 0.7913686982757024], ["Optional[str]", 0.09577257286915655]], "lookup": [["str", 0.22190781025246958], ["List[str]", 0.18811329242980948], ["bool", 0.10708025143418551], ["Dict[str, Type[Any]]", 0.0959263736085877], ["dict", 0.0939317741088954]], "registry": [["dict", 0.3653702080608427], ["str", 0.2045243098986294], ["Tuple[str, str, str, str, str]", 0.14746437895889436], ["list", 0.11962794673524671], ["Dict[str, Type[Any]]", 0.08550636670362816], ["set", 0.0775067896427586]], "repo_name": [["str", 0.3961787379448557], ["Dict[str, str]", 0.3676150062491628], ["set", 0.08945242565909733], ["Dict[int, str]", 0.07591798595892396], ["ClassVar[str]", 0.07083584418796027]]}}, {"docstring": {"func": "Including a tag in the name parameter sent to the docker-py images method does not ", "long_descr": "work consistently. Instead, get the result set for name and manually check if the tag\nexists.", "ret": null}, "fn_lc": [[422, 4], [441, 21]], "fn_var_ln": {"images": [[439, 20], [439, 26]], "lookup": [[434, 12], [434, 18]], "response": [[429, 12], [429, 20]], "tags": [[437, 16], [437, 20]]}, "fn_var_occur": {"images": [["response", "self", "images", "name", "name"], ["images", "response"], ["images", "image"]], "lookup": [["lookup", "name", "tag"], ["tags", "lookup", "tags"]], "response": [["response", "self", "images", "name", "name"], ["images", "response"]], "tags": [["tags", "image", "get"], ["tags", "lookup", "tags"]]}, "name": "_image_lookup", "params": {"name": "", "self": "", "tag": ""}, "params_descr": {"name": "", "self": "", "tag": ""}, "params_occur": {"name": [["response", "self", "images", "name", "name"], ["self", "fail", "name", "str", "exc"], ["lookup", "name", "tag"]], "self": [["response", "self", "images", "name", "name"], ["self", "fail", "name", "str", "exc"]], "tag": [["lookup", "name", "tag"]]}, "params_p": {"args": [], "kwargs": [], "name": [["Optional[str]", 0.3549855381878351], ["str", 0.12768635167928338], ["Optional[Sequence[str]]", 0.09376715439250657], ["Iterable[str]", 0.0907917044986853], ["Optional[Dict[str, Any]]", 0.08355544868731031]], "self": [], "tag": [["str", 0.4934692882507931], ["Optional[Iterable[str]]", 0.12672020652909705], ["Union[str, List[str]]", 0.10521880350290966], ["Callable[[Any], str]", 0.09497562334457398], ["Optional[str]", 0.08777652482987049]]}, "q_name": "AnsibleDockerClient._image_lookup", "ret_exprs": ["return images"], "ret_type": "", "ret_type_p": [["str", 0.2942433880090959], ["int", 0.1203688112971114], ["bool", 0.09733113838475856], ["List[int]", 0.09529824199021647]], "variables": {"images": "", "lookup": "", "response": "", "tags": ""}, "variables_p": {"images": [["str", 0.20556154658383938], ["Dict[Any, str]", 0.19223506119098133], ["bytes", 0.10307908892491903], ["list", 0.10165095368133376], ["Tuple[str]", 0.09882857881621392], ["List[str]", 0.09288710079926893], ["set", 0.09146291842076952]], "lookup": [["Optional[bytes]", 0.14280885755066772], ["Type[Iterator[str]]", 0.09978815471912644], ["list", 0.09700796072466086], ["Set[str]", 0.08552138173508214], ["str", 0.08264947141252128], ["int", 0.07902260567640006]], "response": [["List[str]", 0.21053241645175963], ["Type[tuple]", 0.19271424585531213], ["str", 0.11303816368900221], ["Tuple[Literal, Literal, Literal, Literal, Literal, Literal, Literal, Literal, Literal, Literal, Literal, Literal, Literal, Literal, Literal, Literal, Literal, Literal, Literal, Literal, Literal, Literal, Literal, Literal, Literal, Literal, Literal, Literal, Literal, Literal, Literal, Literal, Literal, Literal, Literal, Literal, Literal, Literal, Literal, Literal, Literal, Literal, Literal, Literal, Literal, Literal, Literal, Literal, Literal, Literal, Literal, Literal, Literal, Literal, Literal, Literal, Literal, Literal, Literal, Literal, Literal, Literal, Literal, Literal, Literal, Literal, Literal, Literal, Literal, Literal, Literal, Literal, Literal, Literal, Literal, Literal, Literal, Literal, Literal, Literal, Literal, Literal, Literal, Literal, Literal, Literal, Literal, Literal, Literal, Literal, Literal, Literal, Literal, Literal, Literal, Literal, Literal, Literal, Literal, Literal, Literal, Literal, Literal, Literal, Literal, Literal, Literal, Literal, Literal, Literal, Literal, Literal, Literal, Literal, Literal, Literal, Literal, Literal, Literal, Literal, Literal, Literal, Literal, Literal, Literal, Literal, Literal, Literal, Literal, Literal, Literal, Literal, Literal, Literal, Literal, Literal, Literal, Literal, Literal, Literal, Literal, Literal, Literal, Literal, Literal, Literal, Literal, Literal, Literal, Literal, Literal, Literal, Literal, Literal, Literal, Literal, Literal, Literal, Literal, Literal, Literal, Literal, Literal, Literal, Literal, Literal, Literal, Literal, Literal, Literal, Literal, Literal, Literal, Literal, Literal, Literal, Literal, Literal, Literal, Literal, Literal, Literal, Literal, Literal, Literal, Literal, Literal, Literal, Literal, Literal, Literal, Literal, Literal, Literal, Literal, Literal, Literal, Literal, Literal, Literal, Literal, Literal, Literal, Literal, Literal, Literal, Literal, Literal, Literal, Literal, Literal, Literal, Literal, Literal, Literal, Literal, Literal, Literal, Literal, Literal, Literal, Literal, Literal, Literal, Literal, Literal, Literal, Literal, Literal, Literal, Literal, Literal, Literal, Literal, Literal, Literal, Literal, Literal, Literal, Literal, Literal, Literal, Literal, Literal, Literal, Literal, Literal, Literal, Literal, Literal, Literal, Literal, Literal, Literal, Literal, Literal]", 0.08884296783671351], ["Dict[str, str]", 0.08866967641859659]], "tags": [["str", 0.406263358283376], ["Optional[str]", 0.23152991932954237], ["dict", 0.18447340550445462], ["Dict[int, Type[Any]]", 0.09503157121722848], ["List[str]", 0.08270174566539851]]}}, {"docstring": {"func": "Pull an image", "long_descr": null, "ret": null}, "fn_lc": [[443, 4], [462, 41]], "fn_var_ln": {"error_detail": [[453, 24], [453, 36]]}, "fn_var_occur": {"error_detail": [["error_detail", "line", "get"], ["self", "fail", "name", "error_detail", "get", "error_detail", "get"]]}, "name": "pull_image", "params": {"name": "", "self": "", "tag": ""}, "params_descr": {"name": "", "self": "", "tag": ""}, "params_occur": {"name": [["self", "log", "name", "tag"], ["self", "pull", "name", "tag", "tag", "stream", "True", "decode", "True"], ["self", "fail", "name", "error_detail", "get", "error_detail", "get"], ["self", "fail", "name", "line", "get"], ["self", "fail", "name", "tag", "str", "exc"], ["self", "find_image", "name", "tag"]], "self": [["self", "log", "name", "tag"], ["self", "pull", "name", "tag", "tag", "stream", "True", "decode", "True"], ["self", "log", "line", "pretty_print", "True"], ["self", "fail", "name", "error_detail", "get", "error_detail", "get"], ["self", "fail", "name", "line", "get"], ["self", "fail", "name", "tag", "str", "exc"], ["self", "find_image", "name", "tag"]], "tag": [["self", "log", "name", "tag"], ["self", "pull", "name", "tag", "tag", "stream", "True", "decode", "True"], ["self", "fail", "name", "tag", "str", "exc"], ["self", "find_image", "name", "tag"]]}, "params_p": {"args": [], "kwargs": [], "name": [["str", 0.6625555423811149], ["Optional[str]", 0.09069266630031651]], "self": [], "tag": [["str", 0.22202813125471998], ["Optional[str]", 0.11803026171921907], ["Container", 0.11537350761812042], ["bool", 0.08955326224796191], ["Optional[List[str]]", 0.08745874173061423]]}, "q_name": "AnsibleDockerClient.pull_image", "ret_exprs": ["return self.find_image(name, tag)"], "ret_type": "", "ret_type_p": [["str", 0.3023018450188333], ["mypy.types.Instance", 0.20006933088581222], ["Type", 0.10158480339346537]], "variables": {"error_detail": ""}, "variables_p": {"error_detail": [["Dict[str, str]", 0.6227492686134815], ["Dict[str, bool]", 0.11513373460881203], ["Dict[str, Union[Any, Any, Any, Any, Any, Any]]", 0.09478905180285863], ["Dict[int, str]", 0.0839476146395062], ["frozenset[str]", 0.08338033033534158]]}}], "name": "AnsibleDockerClient", "q_name": "AnsibleDockerClient", "variables": {}, "variables_p": {}}], "funcs": [{"docstring": {"func": null, "long_descr": null, "ret": null}, "fn_lc": [[86, 0], [105, 110]], "fn_var_ln": {"i": [[99, 4], [99, 5]]}, "fn_var_occur": {"i": [["number", "len", "each", "BYTE_SUFFIXES", "i"], ["int", "number", "len", "each", "i"]]}, "name": "human_to_bytes", "params": {"number": ""}, "params_descr": {"number": ""}, "params_occur": {"number": [["number", "None"], ["isinstance", "number", "int"], ["number", "isdigit"], ["int", "number"], ["number", "BYTE_SUFFIXES", "number", "isdigit"], ["int", "number"], ["number", "len", "each", "BYTE_SUFFIXES", "i"], ["int", "number", "len", "each", "i"], ["ValueError", "number", "join", "BYTE_SUFFIXES"]]}, "params_p": {"args": [], "kwargs": [], "number": [["Optional[int]", 0.566384073762118], ["int", 0.14577714040351022], ["Optional[str]", 0.07461350996742468]]}, "q_name": "human_to_bytes", "ret_exprs": ["return 0", "return number", "return int(number)", "return int(number[:-1])", "return int(number[:-len(each)]) * (1024 ** i)"], "ret_type": "", "ret_type_p": [["float", 0.3333333333606929], ["str", 0.3333333325206192], ["bool", 4.025596155774169e-10]], "variables": {"i": ""}, "variables_p": {"i": [["int", 1.0]]}}], "imports": ["os", "re", "json", "sys", "copy", "distutils", "version", "LooseVersion", "urlparse", "urlparse", "ansible", "module_utils", "basic", "requests", "exceptions", "SSLError", "docker", "Client", "docker", "__version__", "docker_version", "docker", "errors", "APIError", "TLSParameterError", "NotFound", "docker", "tls", "TLSConfig", "docker", "constants", "DEFAULT_TIMEOUT_SECONDS", "DEFAULT_DOCKER_API_VERSION", "docker", "utils", "types", "Ulimit", "LogConfig", "docker", "auth"], "mod_var_ln": {"BYTE_SUFFIXES": [[75, 0], [75, 13]], "DEFAULT_DOCKER_HOST": [[45, 0], [45, 19]], "DEFAULT_DOCKER_REGISTRY": [[73, 0], [73, 23]], "DEFAULT_TLS": [[46, 0], [46, 11]], "DEFAULT_TLS_VERIFY": [[47, 0], [47, 18]], "DOCKER_COMMON_ARGS": [[50, 0], [50, 18]], "DOCKER_MUTUALLY_EXCLUSIVE": [[65, 0], [65, 25]], "DOCKER_REQUIRED_TOGETHER": [[69, 0], [69, 24]], "EMAIL_REGEX": [[74, 0], [74, 11]], "HAS_DOCKER_ERROR": [[42, 4], [42, 20]], "HAS_DOCKER_PY": [[43, 4], [43, 17]], "MIN_DOCKER_VERSION": [[48, 0], [48, 18]]}, "mod_var_occur": {"BYTE_SUFFIXES": [["number", "BYTE_SUFFIXES", "number", "isdigit"], ["BYTE_SUFFIXES"], ["number", "len", "each", "BYTE_SUFFIXES", "i"], ["ValueError", "number", "join", "BYTE_SUFFIXES"]], "DEFAULT_DOCKER_HOST": [["result", "dict", "docker_host", "self", "_get_value", "params", "DEFAULT_DOCKER_HOST", "tls_hostname", "self", "_get_value", "params", "api_version", "self", "_get_value", "params", "cacert_path", "self", "_get_value", "params", "None", "cert_path", "self", "_get_value", "params", "None", "key_path", "self", "_get_value", "params", "None", "ssl_version", "self", "_get_value", "params", "None", "tls", "self", "_get_value", "params", "DEFAULT_TLS", "tls_verify", "self", "_get_value", "params", "DEFAULT_TLS_VERIFY", "timeout", "self", "_get_value", "params", "DEFAULT_TIMEOUT_SECONDS"]], "DEFAULT_DOCKER_REGISTRY": [], "DEFAULT_TLS": [["result", "dict", "docker_host", "self", "_get_value", "params", "DEFAULT_DOCKER_HOST", "tls_hostname", "self", "_get_value", "params", "api_version", "self", "_get_value", "params", "cacert_path", "self", "_get_value", "params", "None", "cert_path", "self", "_get_value", "params", "None", "key_path", "self", "_get_value", "params", "None", "ssl_version", "self", "_get_value", "params", "None", "tls", "self", "_get_value", "params", "DEFAULT_TLS", "tls_verify", "self", "_get_value", "params", "DEFAULT_TLS_VERIFY", "timeout", "self", "_get_value", "params", "DEFAULT_TIMEOUT_SECONDS"]], "DEFAULT_TLS_VERIFY": [["result", "dict", "docker_host", "self", "_get_value", "params", "DEFAULT_DOCKER_HOST", "tls_hostname", "self", "_get_value", "params", "api_version", "self", "_get_value", "params", "cacert_path", "self", "_get_value", "params", "None", "cert_path", "self", "_get_value", "params", "None", "key_path", "self", "_get_value", "params", "None", "ssl_version", "self", "_get_value", "params", "None", "tls", "self", "_get_value", "params", "DEFAULT_TLS", "tls_verify", "self", "_get_value", "params", "DEFAULT_TLS_VERIFY", "timeout", "self", "_get_value", "params", "DEFAULT_TIMEOUT_SECONDS"]], "DOCKER_COMMON_ARGS": [["merged_arg_spec", "update", "DOCKER_COMMON_ARGS"], ["DOCKER_COMMON_ARGS"]], "DOCKER_MUTUALLY_EXCLUSIVE": [["mutually_exclusive_params", "DOCKER_MUTUALLY_EXCLUSIVE"]], "DOCKER_REQUIRED_TOGETHER": [["required_together_params", "DOCKER_REQUIRED_TOGETHER"]], "EMAIL_REGEX": [], "HAS_DOCKER_ERROR": [["self", "fail", "HAS_DOCKER_ERROR"]], "HAS_DOCKER_PY": [["HAS_DOCKER_PY"], ["HAS_DOCKER_PY"]], "MIN_DOCKER_VERSION": [["LooseVersion", "docker_version", "LooseVersion", "MIN_DOCKER_VERSION"], ["self", "fail", "docker_version", "MIN_DOCKER_VERSION"]]}, "no_types_annot": {"D": 0, "I": 0, "U": 85}, "session_id": "tFKiReQrIrEF9ITfgc0o2oap6IuqwuP6TikOsnWnsvE", "set": null, "tc": [false, null], "type_annot_cove": 0.0, "typed_seq": "", "untyped_seq": "", "variables": {"BYTE_SUFFIXES": "", "DEFAULT_DOCKER_HOST": "", "DEFAULT_DOCKER_REGISTRY": "", "DEFAULT_TLS": "", "DEFAULT_TLS_VERIFY": "", "DOCKER_COMMON_ARGS": "", "DOCKER_MUTUALLY_EXCLUSIVE": "", "DOCKER_REQUIRED_TOGETHER": "", "EMAIL_REGEX": "", "HAS_DOCKER_ERROR": "", "HAS_DOCKER_PY": "", "MIN_DOCKER_VERSION": ""}, "variables_p": {"BYTE_SUFFIXES": [["int", 0.8563650745792848], ["float", 0.1436349254207152]], "DEFAULT_DOCKER_HOST": [["str", 0.400735927941932], ["Optional[str]", 0.11968569462417582]], "DEFAULT_DOCKER_REGISTRY": [["str", 0.4396890022893148], ["Tuple[str, str]", 0.16564157429341964], ["Set[str]", 0.14258731849981401], ["Dict[str, List[Any]]", 0.08644053062403174], ["int", 0.08282078714670982], ["float", 0.08282078714670982]], "DEFAULT_TLS": [["str", 0.49392455623991505], ["Dict[str, Dict[str, Any]]", 0.10764825692509683], ["Dict[str, List[Any]]", 0.10585478359713843], ["List[List[Any]]", 0.08715202006805695], ["Dict[str, Any]", 0.08268835494704735]], "DEFAULT_TLS_VERIFY": [["str", 0.49392455623991505], ["Dict[str, Dict[str, Any]]", 0.10764825692509683], ["Dict[str, List[Any]]", 0.10585478359713843], ["List[List[Any]]", 0.08715202006805695], ["Dict[str, Any]", 0.08268835494704735]], "DOCKER_COMMON_ARGS": [["str", 0.36468923498526934]], "DOCKER_MUTUALLY_EXCLUSIVE": [["list", 0.09795248372361673]], "DOCKER_REQUIRED_TOGETHER": [["str", 0.5027631061594061], ["int", 0.19615020742127443], ["List[str]", 0.10145868103225995]], "EMAIL_REGEX": [["str", 0.6], ["Optional[str]", 0.1], ["bool", 0.1], ["Union[Literal, str]", 0.1], ["int", 0.1]], "HAS_DOCKER_ERROR": [["str", 0.701066400053614], ["int", 0.10776611977476114], ["Sequence[int]", 0.10214866716236733], ["bool", 0.08901881300925757]], "HAS_DOCKER_PY": [["List[str]", 0.4200419102765648], ["str", 0.19946730037610155]], "MIN_DOCKER_VERSION": [["list", 0.10694087458113054]]}}}