{"error": null, "response": {"classes": [{"cls_lc": [[25, 0], [83, 22]], "cls_var_ln": {}, "cls_var_occur": {}, "funcs": [{"docstring": {"func": null, "long_descr": null, "ret": null}, "fn_lc": [[36, 4], [48, 35]], "fn_var_ln": {"_algorithm": [[48, 8], [48, 23]], "_audience": [[46, 8], [46, 22]], "_expiration_time_in_seconds": [[45, 8], [45, 40]], "_leeway_in_seconds": [[47, 8], [47, 31]], "_secret_key": [[44, 8], [44, 24]]}, "fn_var_occur": {"_algorithm": [["self", "_algorithm", "algorithm"]], "_audience": [["self", "_audience", "audience"]], "_expiration_time_in_seconds": [["self", "_expiration_time_in_seconds", "expiration_time_in_seconds"]], "_leeway_in_seconds": [["self", "_leeway_in_seconds", "leeway_in_seconds"]], "_secret_key": [["self", "_secret_key", "secret_key"]]}, "name": "__init__", "params": {"algorithm": "builtins.str", "audience": "builtins.str", "expiration_time_in_seconds": "builtins.int", "leeway_in_seconds": "builtins.int", "secret_key": "builtins.str", "self": ""}, "params_descr": {"algorithm": "", "audience": "", "expiration_time_in_seconds": "", "leeway_in_seconds": "", "secret_key": "", "self": ""}, "params_occur": {"algorithm": [["self", "_algorithm", "algorithm"]], "audience": [["self", "_audience", "audience"]], "expiration_time_in_seconds": [["self", "_expiration_time_in_seconds", "expiration_time_in_seconds"]], "leeway_in_seconds": [["self", "_leeway_in_seconds", "leeway_in_seconds"]], "secret_key": [["self", "_secret_key", "secret_key"]], "self": [["self", "_secret_key", "secret_key"], ["self", "_expiration_time_in_seconds", "expiration_time_in_seconds"], ["self", "_audience", "audience"], ["self", "_leeway_in_seconds", "leeway_in_seconds"], ["self", "_algorithm", "algorithm"]]}, "params_p": {"algorithm": [["bool", 0.12082341713861114], ["Optional[int]", 0.12082341713861114], ["float", 0.09719160886087083], ["Exception", 0.09505385138988764], ["Optional[str]", 0.09483723214229335], ["Optional[List[Any]]", 0.09483723214229335], ["Tuple[int, int, int]", 0.09275563823765656], ["Optional[datetime.datetime]", 0.09182364644978562]], "args": [], "audience": [["bool", 0.12082341713861114], ["Optional[int]", 0.12082341713861114], ["float", 0.09719160886087083], ["Exception", 0.09505385138988764], ["Optional[str]", 0.09483723214229335], ["Optional[List[Any]]", 0.09483723214229335], ["Tuple[int, int, int]", 0.09275563823765656], ["Optional[datetime.datetime]", 0.09182364644978562]], "expiration_time_in_seconds": [["int", 0.2886169841689122], ["float", 0.2091387230627843], ["datetime.time.delta", 0.2085519218666641], ["Optional[str]", 0.10782260023640221], ["str", 0.09435222924416196], ["datetime.datetime", 0.09151754142107521]], "kwargs": [], "leeway_in_seconds": [["bool", 0.12082341713861114], ["Optional[int]", 0.12082341713861114], ["float", 0.09719160886087083], ["Exception", 0.09505385138988764], ["Optional[str]", 0.09483723214229335], ["Optional[List[Any]]", 0.09483723214229335], ["Tuple[int, int, int]", 0.09275563823765656], ["Optional[datetime.datetime]", 0.09182364644978562]], "secret_key": [["Dict[str, Any]", 0.17482799317116246], ["bytes", 0.11095299892935546], ["Dict[str, int]", 0.10041754561385793], ["int", 0.0987320043391219], ["Optional[\"TrackingData\"]", 0.09475327826431419], ["bool", 0.0871737263022992], ["Union[bytes, str, None]", 0.0863186165069565]], "self": []}, "q_name": "JWTSigner.__init__", "ret_exprs": [], "ret_type": "", "variables": {"_algorithm": "", "_audience": "", "_expiration_time_in_seconds": "", "_leeway_in_seconds": "", "_secret_key": ""}, "variables_p": {"_algorithm": [["str", 0.30000000000000004], ["Dict[str, Any]", 0.1], ["dict", 0.1], ["int", 0.1]], "_audience": [["str", 0.30000000000000004], ["Dict[str, Any]", 0.1], ["dict", 0.1], ["int", 0.1]], "_expiration_time_in_seconds": [["int", 0.6010394118012273], ["List[int]", 0.1141209260861215], ["str", 0.09721763145575511], ["float", 0.09006814325735861]], "_leeway_in_seconds": [["int", 3.544077907554408e-10]], "_secret_key": [["str", 0.3803193538480458], ["Iterator[Any]", 0.20538558811148366], ["int", 0.20338442039055704], ["bytes", 0.08682551885476303]]}}, {"docstring": {"func": "Generate JWT with extra payload added.", "long_descr": null, "ret": "signed token"}, "fn_lc": [[50, 4], [69, 20]], "fn_var_ln": {"jwt_dict": [[57, 8], [57, 16]], "token": [[64, 8], [64, 13]]}, "fn_var_occur": {"jwt_dict": [["jwt_dict", "self", "_audience", "datetime", "utcnow", "datetime", "utcnow", "datetime", "utcnow", "timedelta", "seconds", "self", "_expiration_time_in_seconds"], ["jwt_dict", "update", "extra_payload"], ["token", "jwt", "encode", "jwt_dict", "self", "_secret_key", "algorithm", "self", "_algorithm"]], "token": [["token", "jwt", "encode", "jwt_dict", "self", "_secret_key", "algorithm", "self", "_algorithm"]]}, "name": "generate_signed_token", "params": {"extra_payload": "builtins.dict[builtins.str, typing.Any]", "self": ""}, "params_descr": {"extra_payload": "extra payload that is added to the signed token", "self": ""}, "params_occur": {"extra_payload": [["jwt_dict", "update", "extra_payload"]], "self": [["jwt_dict", "self", "_audience", "datetime", "utcnow", "datetime", "utcnow", "datetime", "utcnow", "timedelta", "seconds", "self", "_expiration_time_in_seconds"], ["token", "jwt", "encode", "jwt_dict", "self", "_secret_key", "algorithm", "self", "_algorithm"]]}, "params_p": {"args": [], "extra_payload": [["Mapping", 0.22687154955943806], ["Optional[str]", 0.20514011083159], ["dict", 0.16845064400850604], ["Dict[str, Any]", 0.1033454116885146]], "kwargs": [], "self": []}, "q_name": "JWTSigner.generate_signed_token", "ret_exprs": ["return token"], "ret_type": "builtins.str", "ret_type_p": [["str", 0.4851654591988647], ["Dict[str, Any]", 0.11960446072198982], ["List[str]", 0.09246834350766149]], "variables": {"jwt_dict": "", "token": ""}, "variables_p": {"jwt_dict": [["datetime.datetime.datetime", 0.19980935731869706], ["datetime.tzinfo", 0.17959654514224904], ["datetime.date.time.date", 0.13550447677334518], ["datetime.datetime", 0.12025229945259534], ["datetime.timedelta", 0.08756620326174666]], "token": [["bytes", 0.17506876758607356], ["list", 0.13135268088252844], ["str", 0.12685027559479406]]}}, {"docstring": {"func": null, "long_descr": null, "ret": null}, "fn_lc": [[71, 4], [83, 22]], "fn_var_ln": {"payload": [[72, 8], [72, 15]]}, "fn_var_occur": {"payload": [["payload", "jwt", "decode", "token", "self", "_secret_key", "leeway", "timedelta", "seconds", "self", "_leeway_in_seconds", "algorithms", "self", "_algorithm", "options", "True", "audience", "self", "_audience"]]}, "name": "verify_token", "params": {"self": "", "token": "builtins.str"}, "params_descr": {"self": "", "token": ""}, "params_occur": {"self": [["payload", "jwt", "decode", "token", "self", "_secret_key", "leeway", "timedelta", "seconds", "self", "_leeway_in_seconds", "algorithms", "self", "_algorithm", "options", "True", "audience", "self", "_audience"]], "token": [["payload", "jwt", "decode", "token", "self", "_secret_key", "leeway", "timedelta", "seconds", "self", "_leeway_in_seconds", "algorithms", "self", "_algorithm", "options", "True", "audience", "self", "_audience"]]}, "params_p": {"args": [], "kwargs": [], "self": [], "token": [["str", 0.2018470177384138], ["bytes", 0.1703268760236967], ["dict", 0.16974452419782715], ["List[str]", 0.07787033823066133]]}, "q_name": "JWTSigner.verify_token", "ret_exprs": ["return payload"], "ret_type": "builtins.dict[builtins.str, typing.Any]", "ret_type_p": [["str", 0.9999999933355793], ["float", 5.956474712163605e-10]], "variables": {"payload": ""}, "variables_p": {"payload": [["str", 0.301877370252798], ["Dict[str, Union[Any, Any, Any]]", 0.12695660381665402], ["Dict[str, str]", 0.09541834965362576], ["Dict[str, float]", 0.09541834965362576], ["List[str]", 0.09525650671953383], ["Optional[str]", 0.09423612059651117]]}}], "name": "JWTSigner", "q_name": "JWTSigner", "variables": {}, "variables_p": {}}], "funcs": [], "imports": ["__future__", "annotations", "datetime", "datetime", "timedelta", "typing", "Any", "jwt"], "mod_var_ln": {}, "mod_var_occur": {}, "no_types_annot": {"D": 9, "I": 0, "U": 9}, "session_id": "Vq_tVkuaZn8WCGggPGVbEGn5PNE3nH3lxG7xzuGkTvg", "set": null, "tc": [false, null], "type_annot_cove": 0.5, "typed_seq": "", "untyped_seq": "", "variables": {}, "variables_p": {}}}